autotiling/__about__.py
autotiling/__init__.py
autotiling/main.py
autotiling-1.9.3.dist-info/LICENSE
autotiling-1.9.3.dist-info/METADATA
autotiling-1.9.3.dist-info/WHEEL
autotiling-1.9.3.dist-info/entry_points.txt
autotiling-1.9.3.dist-info/top_level.txt
autotiling-1.9.3.dist-info/RECORD
