Metadata-Version: 2.1
Name: autotiling
Version: 1.9.3
Summary: Automatically switch the horizontal/vertical window split orientation in sway and i3
Home-page: https://github.com/nwg-piotr/autotiling
Author: Piotr Miller
Author-email: nwg.piotr@gmail.com
License: GPL-3.0-or-later
Project-URL: Code, https://github.com/nwg-piotr/autotiling
Project-URL: Issues, https://github.com/nwg-piotr/autotiling/issues
Classifier: Development Status :: 4 - Beta
Classifier: License :: OSI Approved :: GNU General Public License v3 or later (GPLv3+)
Classifier: Operating System :: OS Independent
Classifier: Programming Language :: Python
Classifier: Programming Language :: Python :: 3
Classifier: Programming Language :: Python :: 3.6
Classifier: Programming Language :: Python :: 3.7
Classifier: Programming Language :: Python :: 3.8
Classifier: Programming Language :: Python :: 3.9
Classifier: Programming Language :: Python :: 3.10
Requires-Python: >=3.6
License-File: LICENSE
Requires-Dist: i3ipc
Requires-Dist: importlib-metadata ; python_version < "3.8"
